swmclient/__init__.py
swmclient/api.py
swmclient/connection.py
swmclient/logo64.png
swmclient/generated/__init__.py
swmclient/generated/client.py
swmclient/generated/errors.py
swmclient/generated/py.typed
swmclient/generated/types.py
swmclient/generated/api/__init__.py
swmclient/generated/api/default/__init__.py
swmclient/generated/api/default/delete_user_job_job_id.py
swmclient/generated/api/default/get_user_flavor.py
swmclient/generated/api/default/get_user_image.py
swmclient/generated/api/default/get_user_job.py
swmclient/generated/api/default/get_user_job_job_id.py
swmclient/generated/api/default/get_user_job_job_id_stderr.py
swmclient/generated/api/default/get_user_job_job_id_stdout.py
swmclient/generated/api/default/get_user_node.py
swmclient/generated/api/default/get_user_remote.py
swmclient/generated/api/default/patch_user_job_job_id.py
swmclient/generated/api/default/post_user_job.py
swmclient/generated/models/__init__.py
swmclient/generated/models/flavor.py
swmclient/generated/models/image.py
swmclient/generated/models/job.py
swmclient/generated/models/job_state.py
swmclient/generated/models/node.py
swmclient/generated/models/node_role.py
swmclient/generated/models/node_state_alloc.py
swmclient/generated/models/node_state_power.py
swmclient/generated/models/post_user_job_multipart_data.py
swmclient/generated/models/remote_site.py
swmclient/generated/models/resource.py
swmclient-0.1.8.dist-info/LICENSE
swmclient-0.1.8.dist-info/METADATA
swmclient-0.1.8.dist-info/WHEEL
swmclient-0.1.8.dist-info/top_level.txt
swmclient-0.1.8.dist-info/RECORD
