Metadata-Version: 2.1
Name: swmclient
Version: 0.1.8
Summary: Python bindings for swm-core user REST API
Author-email: Taras Shapovalov <taras@iclouds.net>
License: BSD 3-Clause License
Project-URL: Homepage, https://openworkload.org
Project-URL: Documentation, https://openworkload.org
Project-URL: Repository, https://github.com/openworkload/swm-python-client
Project-URL: Tests, https://github.com/openworkload/swm-python-client/tree/master/test
Project-URL: Issues, https://github.com/openworkload/swm-python-client/issues
Project-URL: Distribution, https://pypi.org/project/swmclient
Keywords: hpc,high performance computing,cloud,cloud computing,open workload,sky port
Classifier: Environment :: Console
Classifier: Development Status :: 3 - Alpha
Classifier: Programming Language :: Python :: 3
Classifier: License :: OSI Approved :: BSD License
Classifier: Operating System :: OS Independent
Classifier: Programming Language :: Python :: 3.10
Classifier: Programming Language :: Python :: 3 :: Only
Requires-Python: ~=3.10
License-File: LICENSE
Requires-Dist: httpx
Provides-Extra: build
Requires-Dist: build==1.2.1; extra == "build"
Provides-Extra: publish
Requires-Dist: twine==5.1.1; extra == "publish"
Provides-Extra: test
Requires-Dist: pytest; extra == "test"
